{
"meta":{"test_sets":[],"test_metrics":[],"learn_metrics":[{"best_value":"Min","name":"RMSE"}],"launch_mode":"Train","parameters":"","iteration_count":1000,"learn_sets":["learn"],"name":"experiment"},
"iterations":[
{"learn":[0.839041925],"iteration":0,"passed_time":0.03673579819,"remaining_time":36.69906239},
{"learn":[0.5940680617],"iteration":75,"passed_time":2.557647682,"remaining_time":31.09561129},
{"learn":[0.5017584842],"iteration":150,"passed_time":4.689081409,"remaining_time":26.36443786},
{"learn":[0.4619404181],"iteration":225,"passed_time":6.914305465,"remaining_time":23.6799665},
{"learn":[0.4409442013],"iteration":300,"passed_time":9.137723466,"remaining_time":21.2201618},
{"learn":[0.4272787822],"iteration":375,"passed_time":11.16728945,"remaining_time":18.53294844},
{"learn":[0.4177853576],"iteration":450,"passed_time":13.16540414,"remaining_time":16.02617932},
{"learn":[0.4104600933],"iteration":525,"passed_time":15.16698397,"remaining_time":13.66758631},
{"learn":[0.4043025379],"iteration":600,"passed_time":17.26839658,"remaining_time":11.46437643},
{"learn":[0.398742322],"iteration":675,"passed_time":19.31022477,"remaining_time":9.255196489},
{"learn":[0.3932721064],"iteration":750,"passed_time":21.23012455,"remaining_time":7.039015994},
{"learn":[0.3886257888],"iteration":825,"passed_time":23.32132717,"remaining_time":4.912725095},
{"learn":[0.3842047312],"iteration":900,"passed_time":25.37137952,"remaining_time":2.787754242},
{"learn":[0.3801437466],"iteration":975,"passed_time":27.30341466,"remaining_time":0.6713954425},
{"learn":[0.3788074334],"iteration":999,"passed_time":27.9063057,"remaining_time":0}
]}